streamlit_keycloak/__init__.py
streamlit_keycloak/frontend/public/bootstrap.min.css
streamlit_keycloak/frontend/public/check-sso.html
streamlit_keycloak/frontend/public/index.html
streamlit_keycloak/frontend/public/login.html
streamlit_keycloak/frontend/public/build/bundle.css
streamlit_keycloak/frontend/public/build/bundle.css.map
streamlit_keycloak/frontend/public/build/bundle.js
streamlit_keycloak/frontend/public/build/bundle.js.map
streamlit_keycloak_zpl-1.1.2.dist-info/LICENSE
streamlit_keycloak_zpl-1.1.2.dist-info/METADATA
streamlit_keycloak_zpl-1.1.2.dist-info/WHEEL
streamlit_keycloak_zpl-1.1.2.dist-info/top_level.txt
streamlit_keycloak_zpl-1.1.2.dist-info/RECORD
