Metadata-Version: 2.2
Name: streamlit-keycloak-zpl
Version: 1.1.2
Summary: Keycloak authentication for Streamlit
Home-page: https://github.com/bleumink/streamlit-keycloak
Author: Gideon Bleumink
Author-email: 
Requires-Python: >=3.7
License-File: LICENSE
Requires-Dist: streamlit>=0.63
Dynamic: author
Dynamic: description
Dynamic: description-content-type
Dynamic: home-page
Dynamic: requires-dist
Dynamic: requires-python
Dynamic: summary
